{
  "nameToResources": [
    {
      "productionName": "стільців",
      "resources": [
        "цвяхів",
        "дерева"
      ]
    },
    {
      "productionName": "ліхтариків",
      "resources": [
        "скла",
        "пластику"
      ]
    },
    {
      "productionName": "цукерок",
      "resources": [
        "молока",
        "шоколаду"
      ]
    },
    {
      "productionName": "наметів",
      "resources": [
        "сукна",
        "алюмінію"
      ]
    },
    {
      "productionName": "роботів",
      "resources": [
        "сталі",
        "пластику"
      ]
    },
    {
      "productionName": "деталей",
      "resources": [
        "заліза",
        "срібла",
        "міді",
        "дерева"
      ]
    },
    {
      "productionName": "іграшок",
      "resources": [
        "дерева",
        "заліза",
        "рулонів тканини"
      ]
    }
  ],
  "production": [
    "F1 F2",
    "A B",
    "IX99 3AS",
    "POR12 NG18",
    "Modl03 Modl07",
    "V4T KD3",
    "Корівка Бджілка"
  ],
  "expenses": [
    "часу",
    "грошей"
  ]
}